[
  { "id": "attack", "name": "\u653b\u64ca", "type": "ability", "typeName": "\u80fd\u529b\u7cfb", "sort": 10 },
  { "id": "defense", "name": "\u9632\u79a6", "type": "ability", "typeName": "\u80fd\u529b\u7cfb", "sort": 20 },
  { "id": "speed", "name": "\u901f\u5ea6", "type": "ability", "typeName": "\u80fd\u529b\u7cfb", "sort": 30 },
  { "id": "fire", "name": "\u706b", "type": "element", "typeName": "\u5c6c\u6027\u7cfb", "sort": 110 },
  { "id": "wind", "name": "\u98a8", "type": "element", "typeName": "\u5c6c\u6027\u7cfb", "sort": 120 },
  { "id": "thunder", "name": "\u96f7", "type": "element", "typeName": "\u5c6c\u6027\u7cfb", "sort": 130 },
  { "id": "ice", "name": "\u51b0", "type": "element", "typeName": "\u5c6c\u6027\u7cfb", "sort": 140 },
  { "id": "combo", "name": "\u9023\u64ca", "type": "special", "typeName": "\u7279\u6b8a\u7cfb", "sort": 210 },
  { "id": "critical", "name": "\u66b4\u64ca", "type": "special", "typeName": "\u7279\u6b8a\u7cfb", "sort": 220 },
  { "id": "aura", "name": "\u9738\u6c23", "type": "special", "typeName": "\u7279\u6b8a\u7cfb", "sort": 230 },
  { "id": "strategy", "name": "\u667a\u7565", "type": "special", "typeName": "\u7279\u6b8a\u7cfb", "sort": 240 }
]
